emailable/__init__.py
emailable/client.py
emailable/error.py
emailable/response.py
emailable_backport-1.0.0.dist-info/LICENSE
emailable_backport-1.0.0.dist-info/WHEEL
emailable_backport-1.0.0.dist-info/METADATA
emailable_backport-1.0.0.dist-info/RECORD
