Metadata-Version: 2.1
Name: emailable-backport
Version: 1.0.0
Summary: This is the backport to python 2.7 of the official python wrapper for the Emailable API.
Home-page: https://github.com/bernardoduarte
License: MIT
Keywords: emailable,email,verification
Author: Bernardo Duarte
Author-email: bernardoeiraduarte@gmail.com
Requires-Python: >=2.7,<3.0
Classifier: Development Status :: 5 - Production/Stable
Classifier: Environment :: Web Environment
Classifier: Intended Audience :: Developers
Classifier: License :: OSI Approved :: MIT License
Classifier: Operating System :: OS Independent
Classifier: Programming Language :: Python :: 2
Classifier: Programming Language :: Python :: 2.7
Classifier: Topic :: Software Development :: Libraries
Classifier: Topic :: Utilities
Requires-Dist: requests (>=2.25.1,<3.0.0)
Project-URL: Repository, https://github.com/bernardoduarte/emailable-python-backport
